LICENSE
README.md
setup.py
zlibdb.py
zlibdb.egg-info/PKG-INFO
zlibdb.egg-info/SOURCES.txt
zlibdb.egg-info/dependency_links.txt
zlibdb.egg-info/top_level.txt