Metadata-Version: 2.1
Name: zlibdb
Version: 0.1
Summary: Key-Value database based on zlib and sqlite3
Author: Song
License-File: LICENSE
